[
  {
    "ParameterKey": "EnvironmentParm",
    "ParameterValue": "Staging"
  },
  {
    "ParameterKey": "ApiTierInstanceTypeParm",
    "ParameterValue": "t2.micro"
  },
  {
    "ParameterKey": "ApiTierAmiIdParm",
    "ParameterValue": "ami-4836a428"
  },
  {
    "ParameterKey": "CustomerAppInstanceTypeParm",
    "ParameterValue": "t2.micro"
  },
  {
    "ParameterKey": "CustomerAppAmiIdParm",
    "ParameterValue": "ami-4836a428"
  },
  {
    "ParameterKey": "AppTierVersionNumberParm",
    "ParameterValue": "REPLACEAPPTIERVERSIONNUMBERPARM"
  },
  {
    "ParameterKey": "CodePipelineExecutionRoleArnParm",
    "ParameterValue": "arn:aws:iam::085224677438:role/SpinSci-Entities-1-0-0-sta-CodePipelineServiceRole-IE727LDSOY9G"
  }
]

